nomadic/__init__.py
nomadic/client/__init__.py
nomadic/client/base.py
nomadic/client/http_client.py
nomadic/client/resources/__init__.py
nomadic/client/resources/api_resource.py
nomadic/client/resources/experiment_results.py
nomadic/client/resources/experiments.py
nomadic/client/resources/models.py
nomadic/client/resources/utils.py
nomadic/experiment/__init__.py
nomadic/experiment/base.py
nomadic/experiment/prompt_tuning.py
nomadic/experiment/rag.py
nomadic/experiment/utils.py
nomadic/model/__init__.py
nomadic/model/base.py
nomadic/recipes/__init__.py
nomadic/recipes/ai_safety/__init__.py
nomadic/recipes/ai_safety/abstract_attack_logic.py
nomadic/recipes/ai_safety/ai_safety_experiment.py
nomadic/recipes/ai_safety/evaluators.py
nomadic/recipes/ai_safety/iris_algorithm.py
nomadic/recipes/ai_safety/language_models.py
nomadic/recipes/ai_safety/rl_agent.py
nomadic/recipes/ai_safety/system_prompts.py
nomadic/recipes/ai_safety/tap_algorithm.py
nomadic/result/__init__.py
nomadic/result/base.py
nomadic/tuner/__init__.py
nomadic/tuner/base.py
nomadic/tuner/flaml/__init__.py
nomadic/tuner/flaml/base.py
nomadic/tuner/ray/__init__.py
nomadic/tuner/ray/base.py
nomadic/tuner/tap/__init__.py
nomadic/tuner/tap/base.py
nomadic/util.py
nomadic/visualization.py
nomadic-0.0.1.5.dist-info/LICENSE
nomadic-0.0.1.5.dist-info/METADATA
nomadic-0.0.1.5.dist-info/WHEEL
nomadic-0.0.1.5.dist-info/RECORD
