Metadata-Version: 2.1
Name: nomadic
Version: 0.0.1.5
Summary: Nomadic is an enterprise-grade toolkit for teams to continuously optimize compound AI systems
Home-page: https://nomadicml.com/
License: Apache-2.0
Keywords: LLM,HPO,RAG,data,devtools,optimization,backtesting
Author: Mustafa Bal
Author-email: mustafa@nomadicml.com
Maintainer: Mustafa Bal
Maintainer-email: mustafa@nomadicml.com
Requires-Python: >=3.9,<3.13
Classifier: License :: OSI Approved :: Apache Software License
Classifier: Operating System :: OS Independent
Classifier: Programming Language :: Python :: 3
Classifier: Programming Language :: Python :: 3.9
Classifier: Programming Language :: Python :: 3.10
Classifier: Programming Language :: Python :: 3.11
Classifier: Programming Language :: Python :: 3.12
Classifier: Topic :: Scientific/Engineering :: Artificial Intelligence
Classifier: Topic :: Software Development :: Libraries :: Application Frameworks
Classifier: Topic :: Software Development :: Libraries :: Python Modules
Requires-Dist: dspy-ai (==2.4.17)
Requires-Dist: flaml (>=1.2.0,<2.0.0)
Requires-Dist: llama-index (>=0.10.68,<0.11.0)
Requires-Dist: llama-index-llms-sagemaker-endpoint (>=0.1.3,<0.2.0)
Requires-Dist: llama-index-llms-together (>=0.1.3,<0.2.0)
Requires-Dist: llama-index-llms-vllm (>=0.1.9,<0.2.0)
Requires-Dist: matplotlib (>=3.7.5,<4.0.0)
Requires-Dist: numpy (>=1.24.4,<2.0.0)
Requires-Dist: optuna (>=3.6.1,<4.0.0)
Requires-Dist: pandas (>=2.0.3,<3.0.0)
Requires-Dist: poetry-plugin-dotenv
Requires-Dist: pydantic (>=2.7.1,<3.0.0)
Requires-Dist: ray[tune] (>=2.35.0,<3.0.0)
Requires-Dist: scipy (>=1.10.1,<2.0.0)
Requires-Dist: seaborn (>=0.13.2,<0.14.0)
Project-URL: Documentation, https://docs.nomadicml.com/
Project-URL: Repository, https://github.com/nomadic-ml/nomadic
